pydate/__init__.py
pydate/activities.py
pydate/dessert.py
pydate/food.py
pydate/pickupline.py
pydatenyc-0.1.4.dist-info/LICENSE
pydatenyc-0.1.4.dist-info/METADATA
pydatenyc-0.1.4.dist-info/WHEEL
pydatenyc-0.1.4.dist-info/top_level.txt
pydatenyc-0.1.4.dist-info/RECORD
