Metadata-Version: 2.1
Name: pydatenyc
Version: 0.1.4
Summary: A CLI tool to recommend date ideas in NYC from activity, to a meal, to dessert based on user preferences, and can even recommend a pick up line for you!
License: GNU GENERAL PUBLIC LICENSE
Project-URL: homepage, https://github.com/software-students-fall2023/3-python-package-exercise-threepeat
Project-URL: repository, https://github.com/software-students-fall2023/3-python-package-exercise-threepeat
Project-URL: documentation, https://github.com/software-students-fall2023/3-python-package-exercise-threepeat#readme
Requires-Python: >=3.7
License-File: LICENSE
